{
  "active_asset_list": "",
  "active_site_section_list": "",
  "addon_headers": [],
  "ads_slot_impression": "",
  "api_type": null,
  "application": "6.30.0",
  "asset_ack": "5:5",
  "b_requests": [
    "Linear-MVPD-VDE.xml"
  ],
  "base_file_name": "linear-mvpd-vde.log",
  "base_sql": "initial-data.sql",
  "c_requests": [],
  "cmp_resp_headers": [],
  "compare_cookies": [],
  "compare_response": true,
  "cookie": "",
  "creator": "xmliu",
  "delta_sql": null,
  "description": "linear mvpd vde",
  "diagnostic": false,
  "error_ack": "",
  "fail_if_validation_error": false,
  "fbase_file_name": null,
  "fm_requests": [],
  "fn_requests": [],
  "fo_requests": [],
  "fserver_conf": null,
  "groups": [
    "MRM-CORE - linear"
  ],
  "meta_data": null,
  "metrics": "0",
  "migrated": false,
  "mode": "pusher",
  "name": "linear-mvpd-vde",
  "override_header": "-1",
  "owner": "xmliu",
  "quartitle_ack": "",
  "repeat_cb": "",
  "result_comment": null,
  "retry": 1,
  "server_conf": "adspr_Linear-ADS-1.conf",
  "service": "adserver",
  "sql": "Linear-MVPD-VDE.sql",
  "start_memcached": false,
  "status": "active",
  "to_step": 10,
  "ua_file": "",
  "updated_at": "2020-10-17 11:43:38 +0000",
  "wiki": "https://wiki.freewheel.tv/display/askc/Rebuild+Comcast+P1+Handler+Test+Design"
}
