{
  "active_asset_list": null,
  "active_site_section_list": null,
  "addon_headers": [],
  "ads_slot_impression": "",
  "api_type": null,
  "application": "4.8.0",
  "asset_ack": "0:0",
  "b_requests": [
    "mrm9877_typeb.xml"
  ],
  "base_file_name": "403.log",
  "base_sql": "oltp1.4.sql",
  "c_requests": [
    "9877_1.xml",
    "9877_1_0.xml",
    "9877_1_1.xml",
    "9877_1_2.xml",
    "9877_2_1.xml",
    "9877_4_1.xml",
    "9877_4_2.xml"
  ],
  "cmp_resp_headers": [],
  "compare_cookies": [],
  "compare_response": true,
  "cookie": "",
  "creator": "hrong",
  "delta_sql": null,
  "description": "multiple adUnit, dot creative",
  "diagnostic": false,
  "error_ack": "",
  "fail_if_validation_error": false,
  "fbase_file_name": null,
  "fm_requests": [],
  "fn_requests": [],
  "fo_requests": [],
  "fserver_conf": null,
  "groups": [
    "MRM-CORE - Case with typeB request",
    "MRM-CORE - dot creative dot server",
    "smoke test"
  ],
  "meta_data": null,
  "metrics": "0",
  "migrated": false,
  "mode": null,
  "name": "403",
  "override_header": "-1",
  "owner": "danwu",
  "quartitle_ack": "",
  "repeat_cb": "",
  "result_comment": "obeserve it... the last request failed on release mode",
  "retry": 1,
  "server_conf": "adspr.conf",
  "service": "adserver",
  "sql": "9877_1.sql",
  "start_memcached": false,
  "status": "active",
  "to_step": 10,
  "ua_file": "",
  "updated_at": "2020-10-17 11:43:38 +0000",
  "wiki": "http://wiki.dev.freewheel.tv/x/ehzt"
}
