{
  "active_asset_list": null,
  "active_site_section_list": null,
  "addon_headers": [],
  "ads_slot_impression": "",
  "api_type": null,
  "application": null,
  "asset_ack": "0:0",
  "b_requests": [
    "5595_typeB.xml"
  ],
  "base_file_name": "13230.log",
  "base_sql": "initial-data.sql",
  "c_requests": [
    "FDB-3973.xml",
    "Link_house_ad.xml",
    "Link_house_ad_noInitialIfCompanion.xml",
    "FDB-5535-noVideo.xml",
    "FDB-5595-noVideo-withSlot.xml",
    "FDB-5595-noVideoPlayer.xml",
    "No_paying_ad_deliver.xml",
    "DPRD_1_ever_green_share.xml",
    "DPRD_2_ever_green_share.xml",
    "DPRD_3_ever_green_share.xml",
    "DPRD_4_ever_green_share.xml",
    "DPRD_5_ever_green_share.xml"
  ],
  "cmp_resp_headers": [],
  "compare_cookies": [],
  "compare_response": true,
  "cookie": "",
  "creator": "qlu",
  "delta_sql": null,
  "description": "add new fileds into type C response,house ad crash bug,FDB-5335-no video",
  "diagnostic": false,
  "error_ack": "",
  "fail_if_validation_error": false,
  "fbase_file_name": null,
  "fm_requests": [],
  "fn_requests": [],
  "fo_requests": [],
  "fserver_conf": null,
  "groups": [
    "MRM-CORE - Case with typeB request"
  ],
  "meta_data": null,
  "metrics": "0",
  "migrated": false,
  "mode": null,
  "name": "13230",
  "override_header": "-1",
  "owner": "jhgeng",
  "quartitle_ack": "",
  "repeat_cb": "",
  "result_comment": "failed on realease mode, json",
  "retry": 1,
  "server_conf": "adspr.conf",
  "service": "adserver",
  "sql": "FDB-3973.sql",
  "start_memcached": false,
  "status": "active",
  "to_step": 10,
  "ua_file": "",
  "updated_at": "2020-10-17 11:43:38 +0000",
  "wiki": "http://wiki.dev.freewheel.tv/x/M6ImAQ;,,,,,http://wiki.dev.freewheel.tv/x/rYguAg"
}
